cyborg/__init__.py
cyborg/models.py
cyborg/urls.py
cyborg/templates/cyborg/humans.txt
cyborg/templates/cyborg/robots.txt
django_cyborg-0.2.1.dist-info/DESCRIPTION.rst
django_cyborg-0.2.1.dist-info/METADATA
django_cyborg-0.2.1.dist-info/metadata.json
django_cyborg-0.2.1.dist-info/RECORD
django_cyborg-0.2.1.dist-info/top_level.txt
django_cyborg-0.2.1.dist-info/WHEEL
