Metadata-Version: 2.0
Name: django-cyborg
Version: 0.2.1
Summary: A simple way to add robots.txt and humans.txt to your Django project
Home-page: https://github.com/aaronbassett/django-cyborg
Author: Aaron Bassett
Author-email: aaron@rawtech.io
License: BSD
Keywords: django-cyborg
Platform: UNKNOWN
Classifier: Development Status :: 3 - Alpha
Classifier: Framework :: Django
Classifier: Framework :: Django :: 1.7
Classifier: Framework :: Django :: 1.8
Classifier: Intended Audience :: Developers
Classifier: License :: OSI Approved :: BSD License
Classifier: Natural Language :: English
Classifier: Programming Language :: Python :: 2
Classifier: Programming Language :: Python :: 2.7
Classifier: Programming Language :: Python :: 3
Classifier: Programming Language :: Python :: 3.4
Classifier: Programming Language :: Python :: 3.5
